[{"id":"3381c2156d141c85","type":"inject","z":"53b1ecd405390f45","name":"","props":[],"repeat":"","crontab":"","once":false,"onceDelay":0.1,"topic":"","x":510,"y":520,"wires":[["acfcbb74e110aa82"]]},{"id":"ded5e77f195c9ad1","type":"debug","z":"53b1ecd405390f45","name":"debug 3","active":true,"tosidebar":true,"console":false,"tostatus":false,"complete":"false","statusVal":"","statusType":"auto","x":820,"y":520,"wires":[]},{"id":"acfcbb74e110aa82","type":"pyodide","z":"53b1ecd405390f45","name":"Matplotlib","configuration":"ca5a68ae12dc4395","pythonCode":"import matplotlib\nmatplotlib.use('AGG')\nimport matplotlib.pyplot as plt\nimport io, base64\n\nfig, ax = plt.subplots()\nax.plot([1,2,3,4], [10,20,15,25], marker='o')\nax.set_title(\"Test Graph\")\n\nbuf = io.BytesIO()\nfig.savefig(buf, format='png')\nbuf.seek(0)\nmsg['payload'] = base64.b64encode(buf.read()).decode('ascii')","x":660,"y":520,"wires":[["ded5e77f195c9ad1","83641a9b74a1b6b8"]]},{"id":"83641a9b74a1b6b8","type":"image","z":"53b1ecd405390f45","name":"","width":160,"data":"payload","dataType":"msg","thumbnail":false,"active":true,"pass":false,"outputs":0,"x":840,"y":560,"wires":[]},{"id":"ca5a68ae12dc4395","type":"pyodide-config","name":"","packages":["matplotlib","numpy"]}]